odoo/addons/account_invoice_refund_code/README.rst
odoo/addons/account_invoice_refund_code/__init__.py
odoo/addons/account_invoice_refund_code/__manifest__.py
odoo/addons/account_invoice_refund_code/i18n/account_invoice_refund_code.pot
odoo/addons/account_invoice_refund_code/i18n/es.po
odoo/addons/account_invoice_refund_code/i18n/it.po
odoo/addons/account_invoice_refund_code/models/__init__.py
odoo/addons/account_invoice_refund_code/models/account_journal.py
odoo/addons/account_invoice_refund_code/models/account_move.py
odoo/addons/account_invoice_refund_code/readme/CONTRIBUTORS.rst
odoo/addons/account_invoice_refund_code/readme/DESCRIPTION.rst
odoo/addons/account_invoice_refund_code/readme/USAGE.rst
odoo/addons/account_invoice_refund_code/static/description/icon.png
odoo/addons/account_invoice_refund_code/static/description/index.html
odoo/addons/account_invoice_refund_code/tests/__init__.py
odoo/addons/account_invoice_refund_code/tests/test_refund_code.py
odoo/addons/account_invoice_refund_code/views/account_journal_views.xml
odoo_addon_account_invoice_refund_code-16.0.1.0.0.6.dist-info/METADATA
odoo_addon_account_invoice_refund_code-16.0.1.0.0.6.dist-info/WHEEL
odoo_addon_account_invoice_refund_code-16.0.1.0.0.6.dist-info/top_level.txt
odoo_addon_account_invoice_refund_code-16.0.1.0.0.6.dist-info/RECORD
